[
  {
    "waktu": "00:40WIB",
    "acara": "Elementary S6, Ep 20"
  },
  {
    "waktu": "01:35WIB",
    "acara": "LEGO Masters USA, Ep 9"
  },
  {
    "waktu": "02:30WIB",
    "acara": "The Cube USA, Ep 9"
  },
  {
    "waktu": "03:25WIB",
    "acara": "S.W.A.T. S4, Ep 8"
  },
  {
    "waktu": "04:20WIB",
    "acara": "Resident Alien, Ep 5"
  },
  {
    "waktu": "05:15WIB",
    "acara": "NCIS: New Orleans S6, Ep 9"
  },
  {
    "waktu": "06:10WIB",
    "acara": "Magnum P.I. S2, Ep 8"
  },
  {
    "waktu": "07:05WIB",
    "acara": "Elementary S6, Ep 19"
  },
  {
    "waktu": "08:00WIB",
    "acara": "Elementary S6, Ep 20"
  },
  {
    "waktu": "08:55WIB",
    "acara": "LEGO Masters USA, Ep 9"
  },
  {
    "waktu": "09:50WIB",
    "acara": "The Cube USA, Ep 9"
  },
  {
    "waktu": "10:45WIB",
    "acara": "S.W.A.T. S4, Ep 8"
  },
  {
    "waktu": "11:40WIB",
    "acara": "Resident Alien, Ep 5"
  },
  {
    "waktu": "12:35WIB",
    "acara": "NCIS: New Orleans S6, Ep 9"
  },
  {
    "waktu": "13:30WIB",
    "acara": "The Walking Dead S8, Ep 4"
  },
  {
    "waktu": "14:25WIB",
    "acara": "The Walking Dead S8, Ep 5"
  },
  {
    "waktu": "15:20WIB",
    "acara": "The Walking Dead S8, Ep 6"
  },
  {
    "waktu": "16:15WIB",
    "acara": "Elementary S7, Ep 12"
  },
  {
    "waktu": "17:10WIB",
    "acara": "Elementary S7, Ep 13"
  },
  {
    "waktu": "18:05WIB",
    "acara": "LEGO Masters UK S2, Ep 2"
  },
  {
    "waktu": "19:00WIB",
    "acara": "Tough As Nails S2, Ep 5"
  },
  {
    "waktu": "20:00WIB",
    "acara": "S.W.A.T. S4, Ep 15"
  },
  {
    "waktu": "21:00WIB",
    "acara": "Intelligence, Ep 3"
  },
  {
    "waktu": "21:25WIB",
    "acara": "Intelligence, Ep 4"
  },
  {
    "waktu": "21:55WIB",
    "acara": "NCIS: New Orleans S6, Ep 16"
  },
  {
    "waktu": "22:50WIB",
    "acara": "Magnum P.I. S2, Ep 15"
  },
  {
    "waktu": "23:45WIB",
    "acara": "Elementary S6, Ep 21"
  }
]