[
  {
    "waktu": "00:50WIB",
    "acara": "In Search Of Umami S1, Ep 1"
  },
  {
    "waktu": "01:15WIB",
    "acara": "In Search Of Umami S1, Ep 2"
  },
  {
    "waktu": "01:45WIB",
    "acara": "Bake With Anna Olson S3, Ep 19"
  },
  {
    "waktu": "02:10WIB",
    "acara": "Bake With Anna Olson S3, Ep 20"
  },
  {
    "waktu": "02:40WIB",
    "acara": "Jason Tastes Asia S1, Ep 3"
  },
  {
    "waktu": "03:05WIB",
    "acara": "Jason Tastes Asia S1, Ep 4"
  },
  {
    "waktu": "03:35WIB",
    "acara": "In Search Of Umami S1, Ep 1"
  },
  {
    "waktu": "04:00WIB",
    "acara": "In Search Of Umami S1, Ep 2"
  },
  {
    "waktu": "04:30WIB",
    "acara": "Bake With Anna Olson S3, Ep 20"
  },
  {
    "waktu": "05:00WIB",
    "acara": "Weird Food Diaries S1, Ep 3"
  },
  {
    "waktu": "05:25WIB",
    "acara": "Weird Food Diaries S1, Ep 4"
  },
  {
    "waktu": "05:50WIB",
    "acara": "Food Producer S1, Ep 13"
  },
  {
    "waktu": "06:15WIB",
    "acara": "Food Producer S1, Ep 1"
  },
  {
    "waktu": "06:45WIB",
    "acara": "Healthy-Licious S1, Ep 3"
  },
  {
    "waktu": "07:10WIB",
    "acara": "Healthy-Licious S1, Ep 4"
  },
  {
    "waktu": "07:40WIB",
    "acara": "In Search Of Umami S1, Ep 1"
  },
  {
    "waktu": "08:05WIB",
    "acara": "In Search Of Umami S1, Ep 2"
  },
  {
    "waktu": "08:35WIB",
    "acara": "Good Chef Bad Chef S10, Ep 17"
  },
  {
    "waktu": "09:00WIB",
    "acara": "Good Chef Bad Chef S10, Ep 18"
  },
  {
    "waktu": "09:30WIB",
    "acara": "Old Taste Detective S2, Ep 7"
  },
  {
    "waktu": "10:25WIB",
    "acara": "Everyday Food S1, Ep 3"
  },
  {
    "waktu": "10:50WIB",
    "acara": "Everyday Food S1, Ep 4"
  },
  {
    "waktu": "11:20WIB",
    "acara": "Food Producer S1, Ep 13"
  },
  {
    "waktu": "11:45WIB",
    "acara": "Food Producer S1, Ep 1"
  },
  {
    "waktu": "12:15WIB",
    "acara": "Siba's Bites S1, Ep 7"
  },
  {
    "waktu": "13:10WIB",
    "acara": "Weird Food Diaries S1, Ep 3"
  },
  {
    "waktu": "13:35WIB",
    "acara": "Weird Food Diaries S1, Ep 4"
  },
  {
    "waktu": "14:05WIB",
    "acara": "In Search Of Umami S1, Ep 1"
  },
  {
    "waktu": "14:30WIB",
    "acara": "In Search Of Umami S1, Ep 2"
  },
  {
    "waktu": "15:00WIB",
    "acara": "Good Chef Bad Chef S10, Ep 19"
  },
  {
    "waktu": "15:30WIB",
    "acara": "Good Chef Bad Chef S10, Ep 20"
  },
  {
    "waktu": "16:00WIB",
    "acara": "Healthy-Licious S1, Ep 3"
  },
  {
    "waktu": "16:30WIB",
    "acara": "Healthy-Licious S1, Ep 4"
  },
  {
    "waktu": "17:00WIB",
    "acara": "Bake With Anna Olson S3, Ep 19"
  },
  {
    "waktu": "17:30WIB",
    "acara": "Bake With Anna Olson S3, Ep 20"
  },
  {
    "waktu": "18:00WIB",
    "acara": "Everyday Food S1, Ep 3"
  },
  {
    "waktu": "18:30WIB",
    "acara": "Everyday Food S1, Ep 4"
  },
  {
    "waktu": "19:00WIB",
    "acara": "Jason Tastes Asia S1, Ep 3"
  },
  {
    "waktu": "19:30WIB",
    "acara": "Jason Tastes Asia S1, Ep 4"
  },
  {
    "waktu": "20:00WIB",
    "acara": "Wonderful Indonesia... S1, Ep 3"
  },
  {
    "waktu": "20:30WIB",
    "acara": "Wonderful Indonesia... S1, Ep 4"
  },
  {
    "waktu": "21:00WIB",
    "acara": "Man Fire Food S9, Ep 3"
  },
  {
    "waktu": "21:30WIB",
    "acara": "Man Fire Food S9, Ep 4"
  },
  {
    "waktu": "22:00WIB",
    "acara": "Old Taste Detective S2, Ep 7"
  },
  {
    "waktu": "23:00WIB",
    "acara": "In Search Of Umami S1, Ep 1"
  },
  {
    "waktu": "23:25WIB",
    "acara": "In Search Of Umami S1, Ep 2"
  },
  {
    "waktu": "23:55WIB",
    "acara": "Weird Food Diaries S1, Ep 3"
  }
]