[
  {
    "kota": "Jakarta Barat",
    "prakiraan_cuaca": {
      "malam": "Berawan",
      "icon_malam": "https://www.bmkg.go.id/asset/img/weather_icon/ID/berawan-pm.png",
      "dini_hari": "Cerah Berawan",
      "icon_dini_hari": "https://www.bmkg.go.id/asset/img/weather_icon/ID/cerah%20berawan-pm.png"
    },
    "suhu": "24 - 31 °C",
    "kelembapan": "85 - 100%"
  },
  {
    "kota": "Jakarta Pusat",
    "prakiraan_cuaca": {
      "malam": "Berawan",
      "icon_malam": "https://www.bmkg.go.id/asset/img/weather_icon/ID/berawan-pm.png",
      "dini_hari": "Cerah Berawan",
      "icon_dini_hari": "https://www.bmkg.go.id/asset/img/weather_icon/ID/cerah%20berawan-pm.png"
    },
    "suhu": "25 - 31 °C",
    "kelembapan": "90 - 95%"
  },
  {
    "kota": "Jakarta Selatan",
    "prakiraan_cuaca": {
      "malam": "Berawan",
      "icon_malam": "https://www.bmkg.go.id/asset/img/weather_icon/ID/berawan-pm.png",
      "dini_hari": "Cerah Berawan",
      "icon_dini_hari": "https://www.bmkg.go.id/asset/img/weather_icon/ID/cerah%20berawan-pm.png"
    },
    "suhu": "24 - 30 °C",
    "kelembapan": "85 - 100%"
  },
  {
    "kota": "Jakarta Timur",
    "prakiraan_cuaca": {
      "malam": "Berawan",
      "icon_malam": "https://www.bmkg.go.id/asset/img/weather_icon/ID/berawan-pm.png",
      "dini_hari": "Cerah Berawan",
      "icon_dini_hari": "https://www.bmkg.go.id/asset/img/weather_icon/ID/cerah%20berawan-pm.png"
    },
    "suhu": "24 - 30 °C",
    "kelembapan": "85 - 100%"
  },
  {
    "kota": "Jakarta Utara",
    "prakiraan_cuaca": {
      "malam": "Berawan",
      "icon_malam": "https://www.bmkg.go.id/asset/img/weather_icon/ID/berawan-pm.png",
      "dini_hari": "Cerah Berawan",
      "icon_dini_hari": "https://www.bmkg.go.id/asset/img/weather_icon/ID/cerah%20berawan-pm.png"
    },
    "suhu": "25 - 31 °C",
    "kelembapan": "90 - 95%"
  },
  {
    "kota": "Kepulauan Seribu",
    "prakiraan_cuaca": {
      "malam": "Berawan",
      "icon_malam": "https://www.bmkg.go.id/asset/img/weather_icon/ID/berawan-pm.png",
      "dini_hari": "Berawan",
      "icon_dini_hari": "https://www.bmkg.go.id/asset/img/weather_icon/ID/berawan-pm.png"
    },
    "suhu": "26 - 31 °C",
    "kelembapan": "90 - 95%"
  }
]