[
  {
    "waktu": "00:30WIB",
    "acara": "My Date With Vampire S2"
  },
  {
    "waktu": "01:20WIB",
    "acara": "A Better Tomorrow 3"
  },
  {
    "waktu": "03:25WIB",
    "acara": "Code Of Honour"
  },
  {
    "waktu": "05:00WIB",
    "acara": "Kiss Me Goodbye"
  },
  {
    "waktu": "06:30WIB",
    "acara": "Crying Heart"
  },
  {
    "waktu": "08:20WIB",
    "acara": "All About Ah Long"
  },
  {
    "waktu": "10:00WIB",
    "acara": "The Lunatics"
  },
  {
    "waktu": "11:30WIB",
    "acara": "Set Up"
  },
  {
    "waktu": "13:10WIB",
    "acara": "The Master"
  },
  {
    "waktu": "14:45WIB",
    "acara": "Aces Go Places"
  },
  {
    "waktu": "16:20WIB",
    "acara": "Saga Of The Phoenix"
  },
  {
    "waktu": "17:55WIB",
    "acara": "Happy Ghost 3"
  },
  {
    "waktu": "19:25WIB",
    "acara": "Dr. Wai In The Scripture"
  },
  {
    "waktu": "21:00WIB",
    "acara": "Rouge"
  },
  {
    "waktu": "22:35WIB",
    "acara": "Last Ghost Standing"
  }
]