[
  {
    "waktu": "00:05WIB",
    "acara": "The Ghost Marriage"
  },
  {
    "waktu": "01:40WIB",
    "acara": "Paranormal 911, Ep 5"
  },
  {
    "waktu": "02:30WIB",
    "acara": "Apartmen"
  },
  {
    "waktu": "04:00WIB",
    "acara": "Zoombies"
  },
  {
    "waktu": "05:35WIB",
    "acara": "Untold Body"
  },
  {
    "waktu": "07:15WIB",
    "acara": "Spides, Ep 5"
  },
  {
    "waktu": "08:05WIB",
    "acara": "The Ghost Marriage"
  },
  {
    "waktu": "09:40WIB",
    "acara": "Paranormal 911, Ep 5"
  },
  {
    "waktu": "10:30WIB",
    "acara": "Apartmen"
  },
  {
    "waktu": "12:00WIB",
    "acara": "Zoombies"
  },
  {
    "waktu": "13:35WIB",
    "acara": "Untold Body"
  },
  {
    "waktu": "15:15WIB",
    "acara": "Spides, Ep 5"
  },
  {
    "waktu": "16:05WIB",
    "acara": "The Ghost Marriage"
  },
  {
    "waktu": "17:40WIB",
    "acara": "Paranormal 911, Ep 5"
  },
  {
    "waktu": "18:30WIB",
    "acara": "Apartmen"
  },
  {
    "waktu": "20:00WIB",
    "acara": "Bell Chamber"
  },
  {
    "waktu": "21:30WIB",
    "acara": "The Spell"
  },
  {
    "waktu": "22:55WIB",
    "acara": "Spides, Ep 6"
  },
  {
    "waktu": "23:50WIB",
    "acara": "She Is In Danger"
  }
]