[
  {
    "mata_uang": "AUD",
    "nama_mata_uang": "AUSTRALIAN DOLLAR",
    "kurs_beli": "10.565,89",
    "kurs_jual": "10.457,68"
  },
  {
    "mata_uang": "BND",
    "nama_mata_uang": "BRUNEI DOLLAR",
    "kurs_beli": "11.468,20",
    "kurs_jual": "11.349,88"
  },
  {
    "mata_uang": "CAD",
    "nama_mata_uang": "CANADIAN DOLLAR",
    "kurs_beli": "11.536,46",
    "kurs_jual": "11.418,26"
  },
  {
    "mata_uang": "CHF",
    "nama_mata_uang": "SWISS FRANC",
    "kurs_beli": "16.562,86",
    "kurs_jual": "16.391,04"
  },
  {
    "mata_uang": "CNH",
    "nama_mata_uang": "CHINA YUAN",
    "kurs_beli": "2.203,80",
    "kurs_jual": "2.181,75"
  },
  {
    "mata_uang": "CNY",
    "nama_mata_uang": "CHINA YUAN",
    "kurs_beli": "2.202,73",
    "kurs_jual": "2.179,98"
  },
  {
    "mata_uang": "DKK",
    "nama_mata_uang": "DANISH KRONE",
    "kurs_beli": "2.193,29",
    "kurs_jual": "2.171,16"
  },
  {
    "mata_uang": "EUR",
    "nama_mata_uang": "EURO",
    "kurs_beli": "16.312,47",
    "kurs_jual": "16.144,01"
  },
  {
    "mata_uang": "GBP",
    "nama_mata_uang": "BRITISH POUND",
    "kurs_beli": "18.999,69",
    "kurs_jual": "18.804,48"
  },
  {
    "mata_uang": "HKD",
    "nama_mata_uang": "HONGKONG DOLLAR",
    "kurs_beli": "1.993,03",
    "kurs_jual": "1.973,17"
  },
  {
    "mata_uang": "JPY",
    "nama_mata_uang": "JAPANESE YEN",
    "kurs_beli": "11.508,20",
    "kurs_jual": "11.391,15"
  },
  {
    "mata_uang": "KRW",
    "nama_mata_uang": "KOREAN WON",
    "kurs_beli": "11,94",
    "kurs_jual": "11,82"
  },
  {
    "mata_uang": "KWD",
    "nama_mata_uang": "KUWAITI DINAR",
    "kurs_beli": "50.576,18",
    "kurs_jual": "50.056,57"
  },
  {
    "mata_uang": "LAK",
    "nama_mata_uang": "LAOTIAN KIP",
    "kurs_beli": "0,90",
    "kurs_jual": "0,88"
  },
  {
    "mata_uang": "MYR",
    "nama_mata_uang": "MALAYSIAN RINGGIT",
    "kurs_beli": "3.531,35",
    "kurs_jual": "3.490,64"
  },
  {
    "mata_uang": "NOK",
    "nama_mata_uang": "NORWEGIAN KRONE",
    "kurs_beli": "1.593,97",
    "kurs_jual": "1.577,62"
  },
  {
    "mata_uang": "NZD",
    "nama_mata_uang": "NEW ZEALAND DOLLAR",
    "kurs_beli": "9.908,43",
    "kurs_jual": "9.803,69"
  },
  {
    "mata_uang": "PGK",
    "nama_mata_uang": "PAPUA N.G. KINA",
    "kurs_beli": "4.535,55",
    "kurs_jual": "4.229,43"
  },
  {
    "mata_uang": "PHP",
    "nama_mata_uang": "PHILIPPINES PESO",
    "kurs_beli": "278,24",
    "kurs_jual": "275,42"
  },
  {
    "mata_uang": "SAR",
    "nama_mata_uang": "SAUDI ARABIAN RIYAL",
    "kurs_beli": "4.125,62",
    "kurs_jual": "4.083,48"
  },
  {
    "mata_uang": "SEK",
    "nama_mata_uang": "SWEDISH KRONA",
    "kurs_beli": "1.503,96",
    "kurs_jual": "1.488,56"
  },
  {
    "mata_uang": "SGD",
    "nama_mata_uang": "SINGAPORE DOLLAR",
    "kurs_beli": "11.468,20",
    "kurs_jual": "11.349,88"
  },
  {
    "mata_uang": "THB",
    "nama_mata_uang": "THAI BAHT",
    "kurs_beli": "446,61",
    "kurs_jual": "441,78"
  },
  {
    "mata_uang": "USD",
    "nama_mata_uang": "US DOLLAR",
    "kurs_beli": "15.506,15",
    "kurs_jual": "15.351,85"
  },
  {
    "mata_uang": "VND",
    "nama_mata_uang": "VIETNAMESE DONG",
    "kurs_beli": "0,64",
    "kurs_jual": "0,63"
  }
]