[
  {
    "waktu": "00:00WIB",
    "acara": "Write With Miao Mi, Ep 92"
  },
  {
    "waktu": "00:03WIB",
    "acara": "Egg Car, Ep 15"
  },
  {
    "waktu": "00:18WIB",
    "acara": "Egg Car, Ep 16"
  },
  {
    "waktu": "00:33WIB",
    "acara": "Miao Mi Classroom, Ep 295"
  },
  {
    "waktu": "00:36WIB",
    "acara": "Jili And Gulu, Ep 27"
  },
  {
    "waktu": "00:45WIB",
    "acara": "Silly Wolf & His Buddies, Ep 25"
  },
  {
    "waktu": "01:00WIB",
    "acara": "Write With Miao Mi, Ep 92"
  },
  {
    "waktu": "01:03WIB",
    "acara": "Emmy & GooRoo S1, Ep 37"
  },
  {
    "waktu": "01:16WIB",
    "acara": "Emmy & GooRoo S1, Ep 38"
  },
  {
    "waktu": "01:28WIB",
    "acara": "Miao Mi Classroom, Ep 295"
  },
  {
    "waktu": "01:31WIB",
    "acara": "Fantastic Circus... S1, Ep 22"
  },
  {
    "waktu": "01:46WIB",
    "acara": "Naughty Elfin, Ep 22"
  },
  {
    "waktu": "01:53WIB",
    "acara": "Naughty Elfin, Ep 23"
  },
  {
    "waktu": "02:00WIB",
    "acara": "Write With Miao Mi, Ep 92"
  },
  {
    "waktu": "02:03WIB",
    "acara": "Tubo Rabbit, Ep 28"
  },
  {
    "waktu": "02:12WIB",
    "acara": "Rainbow Chicks S3, Ep 13"
  },
  {
    "waktu": "02:21WIB",
    "acara": "Rainbow Chicks S3, Ep 14"
  },
  {
    "waktu": "02:30WIB",
    "acara": "Miao Mi Classroom, Ep 295"
  },
  {
    "waktu": "02:33WIB",
    "acara": "A Little Artist Remy..., Ep 37"
  },
  {
    "waktu": "02:43WIB",
    "acara": "A Little Artist Remy..., Ep 38"
  },
  {
    "waktu": "02:53WIB",
    "acara": "Emmy & GooRoo S2, Ep 28"
  },
  {
    "waktu": "03:00WIB",
    "acara": "Write With Miao Mi, Ep 92"
  },
  {
    "waktu": "03:03WIB",
    "acara": "Egg Car, Ep 15"
  },
  {
    "waktu": "03:18WIB",
    "acara": "Egg Car, Ep 16"
  },
  {
    "waktu": "03:33WIB",
    "acara": "Miao Mi Classroom, Ep 295"
  },
  {
    "waktu": "03:36WIB",
    "acara": "Jili And Gulu, Ep 27"
  },
  {
    "waktu": "03:45WIB",
    "acara": "Silly Wolf & His Buddies, Ep 25"
  },
  {
    "waktu": "04:00WIB",
    "acara": "Write With Miao Mi, Ep 92"
  },
  {
    "waktu": "04:03WIB",
    "acara": "Emmy & GooRoo S1, Ep 37"
  },
  {
    "waktu": "04:16WIB",
    "acara": "Emmy & GooRoo S1, Ep 38"
  },
  {
    "waktu": "04:28WIB",
    "acara": "Miao Mi Classroom, Ep 295"
  },
  {
    "waktu": "04:31WIB",
    "acara": "Fantastic Circus... S1, Ep 22"
  },
  {
    "waktu": "04:46WIB",
    "acara": "Naughty Elfin, Ep 22"
  },
  {
    "waktu": "04:53WIB",
    "acara": "Naughty Elfin, Ep 23"
  },
  {
    "waktu": "05:00WIB",
    "acara": "Write With Miao Mi, Ep 92"
  },
  {
    "waktu": "05:03WIB",
    "acara": "Tubo Rabbit, Ep 29"
  },
  {
    "waktu": "05:12WIB",
    "acara": "Rainbow Chicks S3, Ep 14"
  },
  {
    "waktu": "05:21WIB",
    "acara": "Rainbow Chicks S3, Ep 15"
  },
  {
    "waktu": "05:30WIB",
    "acara": "Miao Mi Classroom, Ep 232"
  },
  {
    "waktu": "05:33WIB",
    "acara": "A Little Artist Remy..., Ep 38"
  },
  {
    "waktu": "05:43WIB",
    "acara": "A Little Artist Remy..., Ep 39"
  },
  {
    "waktu": "05:53WIB",
    "acara": "Emmy & GooRoo S2, Ep 29"
  },
  {
    "waktu": "06:00WIB",
    "acara": "Write With Miao Mi, Ep 92"
  },
  {
    "waktu": "06:03WIB",
    "acara": "Egg Car, Ep 16"
  },
  {
    "waktu": "06:18WIB",
    "acara": "Egg Car, Ep 17"
  },
  {
    "waktu": "06:33WIB",
    "acara": "Miao Mi Classroom, Ep 232"
  },
  {
    "waktu": "06:36WIB",
    "acara": "Jili And Gulu, Ep 28"
  },
  {
    "waktu": "06:45WIB",
    "acara": "Silly Wolf & His Buddies, Ep 26"
  },
  {
    "waktu": "07:00WIB",
    "acara": "Write With Miao Mi, Ep 92"
  },
  {
    "waktu": "07:03WIB",
    "acara": "Emmy & GooRoo S1, Ep 38"
  }
]