[
  {
    "waktu": "06/09/2024 03:13:40 WIB",
    "lintang": "8.17 LS",
    "bujur": "115.19 BT",
    "magnitudo": "3",
    "kedalaman": "10 Km",
    "wilayah": "Pusat gempa berada di darat 12 km tenggara Buleleng",
    "warning": [
      "II Buleleng"
    ]
  },
  {
    "waktu": "05/09/2024 14:20:18 WIB",
    "lintang": "7.21 LS",
    "bujur": "107.55 BT",
    "magnitudo": "3.2",
    "kedalaman": "13 Km",
    "wilayah": "Pusat gempa berada di darat 21 km tenggara Kab. Bandung",
    "warning": [
      "II - III Pangalengan",
      "II - III Cibereum",
      "II - III Cimaung",
      "II - III Ciwidey"
    ]
  },
  {
    "waktu": "05/09/2024 12:28:07 WIB",
    "lintang": "4.44 LU",
    "bujur": "96.59 BT",
    "magnitudo": "4",
    "kedalaman": "5 Km",
    "wilayah": "Pusat gempa berada di darat 35 km barat daya Takengon-Aceh Tengah",
    "warning": [
      "II Takengon",
      "II Bener Meriah"
    ]
  },
  {
    "waktu": "05/09/2024 11:31:29 WIB",
    "lintang": "0.22 LS",
    "bujur": "124.61 BT",
    "magnitudo": "5.1",
    "kedalaman": "10 Km",
    "wilayah": "Pusat gempa berada di laut 95 Km tenggara Bolaanguki",
    "warning": [
      "II-III  Kab.Minahasa",
      "II-III Kab.Minahasa Selatan",
      "II-III Kotamobagu",
      "II-III Kab. Bolaang Mongondow",
      "II-III Kab. Bolaang Mongondow Selatan",
      "II-III Kab. Bolaang Mongondow Timur"
    ]
  },
  {
    "waktu": "04/09/2024 13:24:17 WIB",
    "lintang": "6.88 LS",
    "bujur": "107.51 BT",
    "magnitudo": "1.8",
    "kedalaman": "26 Km",
    "wilayah": "Pusat gempa berada di darat 4 km Barat Daya Kab. Bandung",
    "warning": [
      "II Kab. Bandung Barat"
    ]
  },
  {
    "waktu": "03/09/2024 20:43:45 WIB",
    "lintang": "2.54 LS",
    "bujur": "121.14 BT",
    "magnitudo": "2.7",
    "kedalaman": "4 Km",
    "wilayah": "Pusat gempa berada di darat 5 km barat laut Luwuk Timur",
    "warning": [
      "II Wasuponda"
    ]
  },
  {
    "waktu": "03/09/2024 20:13:08 WIB",
    "lintang": "0.35 LS",
    "bujur": "123.1 BT",
    "magnitudo": "4.9",
    "kedalaman": "36 Km",
    "wilayah": "Pusat gempa berada di laut 98 km barat daya Bonebolango",
    "warning": [
      "III Luwuk"
    ]
  },
  {
    "waktu": "03/09/2024 19:43:40 WIB",
    "lintang": "2 LS",
    "bujur": "125.55 BT",
    "magnitudo": "4.4",
    "kedalaman": "14 Km",
    "wilayah": "Pusat gempa berada di laut 49 km barat Sanana",
    "warning": [
      "III Sanana"
    ]
  },
  {
    "waktu": "03/09/2024 06:26:12 WIB",
    "lintang": "2.54 LS",
    "bujur": "121.18 BT",
    "magnitudo": "4.1",
    "kedalaman": "5 Km",
    "wilayah": "Pusat gempa berada di darat 4 km timur laut Luwu Timur",
    "warning": [
      "III Malili"
    ]
  },
  {
    "waktu": "02/09/2024 20:51:28 WIB",
    "lintang": "4.86 LU",
    "bujur": "96.06 BT",
    "magnitudo": "4.7",
    "kedalaman": "5 Km",
    "wilayah": "Pusat gempa berada di darat 28 km barat daya Kab Pidie Jaya",
    "warning": [
      "IV Mane",
      "III Calang",
      "II-III Nagan Raya"
    ]
  },
  {
    "waktu": "02/09/2024 07:39:09 WIB",
    "lintang": "4.53 LU",
    "bujur": "96.43 BT",
    "magnitudo": "4.9",
    "kedalaman": "10 Km",
    "wilayah": "Pusat gempa berada di darat 35 Km TimurLaut Nagan Raya Aceh",
    "warning": [
      "II Aceh Besar",
      "II - III Banda Aceh",
      "II - III Pidie Jaya",
      "III-IV Bener Meriah",
      "III - IV Takengon"
    ]
  },
  {
    "waktu": "02/09/2024 02:59:25 WIB",
    "lintang": "3.81 LU",
    "bujur": "126.68 BT",
    "magnitudo": "5.1",
    "kedalaman": "21 Km",
    "wilayah": "Pusat gempa berada di laut 21 km Tenggara Melonguane",
    "warning": [
      "IV Melonguane",
      "II - III Tahuna",
      "II - III Ondong",
      "II-III Tobelo",
      "II - III Daruba"
    ]
  },
  {
    "waktu": "02/09/2024 01:48:52 WIB",
    "lintang": "4.04 LS",
    "bujur": "121.82 BT",
    "magnitudo": "2.7",
    "kedalaman": "5 Km",
    "wilayah": "Pusat gempa berada di darat 4.4 tenggara Lalolae, Kab. Kolaka Timur",
    "warning": [
      "II - III Mowewe"
    ]
  },
  {
    "waktu": "01/09/2024 18:47:03 WIB",
    "lintang": "2.05 LS",
    "bujur": "125.77 BT",
    "magnitudo": "4.4",
    "kedalaman": "18 Km",
    "wilayah": "Pusat gempa berada di laut 24 km barat Sanana",
    "warning": [
      "III Sanana"
    ]
  },
  {
    "waktu": "01/09/2024 18:41:10 WIB",
    "lintang": "6.72 LS",
    "bujur": "106.65 BT",
    "magnitudo": "2.8",
    "kedalaman": "12 Km",
    "wilayah": "Pusat gempa berada di darat 21 km barat daya Kota Bogor",
    "warning": [
      "II Kec. Pamijahan"
    ]
  },
  {
    "waktu": "31/08/2024 15:53:48 WIB",
    "lintang": "3.28 LS",
    "bujur": "140.03 BT",
    "magnitudo": "5.2",
    "kedalaman": "93 Km",
    "wilayah": "Pusat gempa berada di darat 81 km barat laut Keerom",
    "warning": [
      "II Wamena"
    ]
  },
  {
    "waktu": "31/08/2024 15:04:42 WIB",
    "lintang": "4.16 LS",
    "bujur": "121.7 BT",
    "magnitudo": "2.5",
    "kedalaman": "5 Km",
    "wilayah": "Pusat gempa berada di darat 3.4 Km TimurLaut Baula, Kab.Kolaka",
    "warning": [
      "II-III Wundulako"
    ]
  },
  {
    "waktu": "31/08/2024 01:06:57 WIB",
    "lintang": "4.9 LS",
    "bujur": "122.69 BT",
    "magnitudo": "2.7",
    "kedalaman": "5 Km",
    "wilayah": "Pusat gempa berada di darat 5 km barat daya Duruka, Kab. Muna",
    "warning": [
      "III Muna"
    ]
  },
  {
    "waktu": "28/08/2024 10:36:48 WIB",
    "lintang": "7.74 LS",
    "bujur": "107.84 BT",
    "magnitudo": "3.4",
    "kedalaman": "5 Km",
    "wilayah": "Pusat gempa berada di Laut 51 Km BaratDaya KAB-TASIKMALAYA",
    "warning": [
      "III Cipatujah",
      "III Cibalong",
      "III Pamengpeuk"
    ]
  },
  {
    "waktu": "27/08/2024 09:40:39 WIB",
    "lintang": "9.55 LS",
    "bujur": "118.59 BT",
    "magnitudo": "4.9",
    "kedalaman": "19 Km",
    "wilayah": "Pusat gempa berada di laut 44 km barat laut Kodi",
    "warning": [
      "III Tambolaka"
    ]
  }
]