[
  {
    "waktu": "20-07-23 10:31:35 WIB",
    "lintang": "-1.47",
    "bujur": "126.38",
    "magnitudo": "5.2",
    "kedalaman": "10 Km",
    "wilayah": "75 km TimurLaut SANANA-MALUT"
  },
  {
    "waktu": "20-07-23 06:08:08 WIB",
    "lintang": "3.04",
    "bujur": "128.36",
    "magnitudo": "5.4",
    "kedalaman": "199 Km",
    "wilayah": "105 km TimurLaut PULAUDOI-MALUT"
  },
  {
    "waktu": "19-07-23 22:18:49 WIB",
    "lintang": "-3.06",
    "bujur": "139.99",
    "magnitudo": "5.2",
    "kedalaman": "18 Km",
    "wilayah": "70 km BaratDaya KAB-JAYAPURA-PAPUA"
  },
  {
    "waktu": "19-07-23 17:47:53 WIB",
    "lintang": "-2.38",
    "bujur": "122.71",
    "magnitudo": "5.0",
    "kedalaman": "10 Km",
    "wilayah": "96 km TimurLaut MOROWALI-SULTENG"
  },
  {
    "waktu": "17-07-23 22:35:27 WIB",
    "lintang": "5.69",
    "bujur": "124.14",
    "magnitudo": "5.1",
    "kedalaman": "10 Km",
    "wilayah": "275 km BaratLaut TAHUNA-KEP.SANGIHE-SULUT"
  },
  {
    "waktu": "17-07-23 16:46:36 WIB",
    "lintang": "-1.44",
    "bujur": "126.41",
    "magnitudo": "5.2",
    "kedalaman": "10 Km",
    "wilayah": "80 km TimurLaut SANANA-MALUT"
  },
  {
    "waktu": "17-07-23 11:42:16 WIB",
    "lintang": "-1.46",
    "bujur": "126.42",
    "magnitudo": "5.8",
    "kedalaman": "10 Km",
    "wilayah": "79 km TimurLaut SANANA-MALUT"
  },
  {
    "waktu": "12-07-23 15:39:35 WIB",
    "lintang": "-10.01",
    "bujur": "118.81",
    "magnitudo": "5.3",
    "kedalaman": "10 Km",
    "wilayah": "50 km BaratDaya KODI-SUMBABARATDAYA-NTT"
  },
  {
    "waktu": "10-07-23 08:19:04 WIB",
    "lintang": "3.65",
    "bujur": "95.84",
    "magnitudo": "5.2",
    "kedalaman": "27 Km",
    "wilayah": "63 km BaratDaya MEULABOH-ACEHBARAT"
  },
  {
    "waktu": "09-07-23 21:09:06 WIB",
    "lintang": "5.38",
    "bujur": "94.77",
    "magnitudo": "5.5",
    "kedalaman": "24 Km",
    "wilayah": "64 km BaratDaya BANDAACEH-ACEH"
  },
  {
    "waktu": "07-07-23 11:25:08 WIB",
    "lintang": "-2.40",
    "bujur": "140.07",
    "magnitudo": "5.0",
    "kedalaman": "28 Km",
    "wilayah": "42 km BaratLaut KAB-JAYAPURA-PAPUA"
  },
  {
    "waktu": "07-07-23 00:13:19 WIB",
    "lintang": "-7.17",
    "bujur": "129.62",
    "magnitudo": "6.0",
    "kedalaman": "162 Km",
    "wilayah": "207 km BaratLaut TANIBAR"
  },
  {
    "waktu": "03-07-23 09:51:38 WIB",
    "lintang": "-3.71",
    "bujur": "140.25",
    "magnitudo": "6.2",
    "kedalaman": "33 Km",
    "wilayah": "69 km BaratDaya KEEROM-PAPUA"
  },
  {
    "waktu": "02-07-23 01:44:18 WIB",
    "lintang": "-7.89",
    "bujur": "117.66",
    "magnitudo": "5.0",
    "kedalaman": "31 Km",
    "wilayah": "71 km TimurLaut SUMBAWA-NTB"
  },
  {
    "waktu": "30-06-23 19:57:43 WIB",
    "lintang": "-8.63",
    "bujur": "110.08",
    "magnitudo": "6.4",
    "kedalaman": "25 Km",
    "wilayah": "86 km BaratDaya BANTUL-DIY"
  },
  {
    "waktu": "30-06-23 17:37:31 WIB",
    "lintang": "-0.59",
    "bujur": "122.44",
    "magnitudo": "5.3",
    "kedalaman": "10 Km",
    "wilayah": "103 km BaratLaut BANGGAIKEP-SULTENG"
  },
  {
    "waktu": "30-06-23 17:29:48 WIB",
    "lintang": "3.60",
    "bujur": "127.94",
    "magnitudo": "5.0",
    "kedalaman": "94 Km",
    "wilayah": "146 km TimurLaut PULAUDOI-MALUT"
  },
  {
    "waktu": "30-06-23 09:00:38 WIB",
    "lintang": "-6.99",
    "bujur": "129.67",
    "magnitudo": "5.1",
    "kedalaman": "160 Km",
    "wilayah": "211 km BaratLaut TANIBAR"
  },
  {
    "waktu": "29-06-23 20:52:47 WIB",
    "lintang": "4.90",
    "bujur": "126.04",
    "magnitudo": "5.0",
    "kedalaman": "104 Km",
    "wilayah": "116 km BaratLaut PULAUKARATUNG-SULUT"
  },
  {
    "waktu": "27-06-23 23:55:17 WIB",
    "lintang": "-7.35",
    "bujur": "130.22",
    "magnitudo": "5.5",
    "kedalaman": "123 Km",
    "wilayah": "139 km BaratLaut TANIBAR"
  },
  {
    "waktu": "26-06-23 17:12:37 WIB",
    "lintang": "2.13",
    "bujur": "98.41",
    "magnitudo": "5.1",
    "kedalaman": "71 Km",
    "wilayah": "40 km BaratDaya HUMBANGHASUNDUTAN-SUMUT"
  },
  {
    "waktu": "20-06-23 15:39:18 WIB",
    "lintang": "-0.91",
    "bujur": "98.55",
    "magnitudo": "5.8",
    "kedalaman": "10 Km",
    "wilayah": "166 km BaratLaut KEP-MENTAWAI-SUMBAR"
  },
  {
    "waktu": "16-06-23 01:06:22 WIB",
    "lintang": "-22.82",
    "bujur": "176.44",
    "magnitudo": "6.9",
    "kedalaman": "161 Km",
    "wilayah": "771 km BaratDaya SUVA-FIJIISLAND"
  },
  {
    "waktu": "12-06-23 10:17:05 WIB",
    "lintang": "-7.29",
    "bujur": "130.17",
    "magnitudo": "5.1",
    "kedalaman": "147 Km",
    "wilayah": "147 km BaratLaut TANIBAR"
  },
  {
    "waktu": "11-06-23 13:51:49 WIB",
    "lintang": "-2.68",
    "bujur": "136.70",
    "magnitudo": "5.2",
    "kedalaman": "48 Km",
    "wilayah": "18 km TimurLaut WAROPEN-PAPUA"
  },
  {
    "waktu": "11-06-23 08:42:32 WIB",
    "lintang": "-0.04",
    "bujur": "123.08",
    "magnitudo": "5.4",
    "kedalaman": "121 Km",
    "wilayah": "64 km BaratDaya BONEBOLANGO-GORONTALO"
  },
  {
    "waktu": "08-06-23 00:04:55 WIB",
    "lintang": "-9.15",
    "bujur": "110.69",
    "magnitudo": "6.0",
    "kedalaman": "10 Km",
    "wilayah": "117 km BaratDaya PACITAN-JATIM"
  },
  {
    "waktu": "06-06-23 14:23:04 WIB",
    "lintang": "-8.05",
    "bujur": "107.01",
    "magnitudo": "5.1",
    "kedalaman": "10 Km",
    "wilayah": "126 km Tenggara KOTA-SUKABUMI-JABAR"
  },
  {
    "waktu": "05-06-23 20:08:49 WIB",
    "lintang": "-10.02",
    "bujur": "118.84",
    "magnitudo": "5.0",
    "kedalaman": "10 Km",
    "wilayah": "50 km BaratDaya KODI-SUMBABARATDAYA-NTT"
  },
  {
    "waktu": "04-06-23 21:55:28 WIB",
    "lintang": "1.60",
    "bujur": "125.73",
    "magnitudo": "5.1",
    "kedalaman": "111 Km",
    "wilayah": "69 km TimurLaut BITUNG-SULUT"
  }
]